drum/__init__.py
drum/links/__init__.py
drum/links/admin.py
drum/links/forms.py
drum/links/models.py
drum/links/urls.py
drum/links/utils.py
drum/links/views.py
drum/links/management/__init__.py
drum/links/management/commands/__init__.py
drum/links/management/commands/auto_tag.py
drum/links/management/commands/poll_rss.py
drum/links/management/commands/poll_tumblr.py
drum/links/migrations/0001_initial.py
drum/links/migrations/__init__.py
drum/links/static/css/bootstrap2-responsive.css
drum/links/static/css/bootstrap2.css
drum/links/static/css/drum.css
drum/links/static/css/flat-ui.css
drum/links/static/css/keywords.css
drum/links/static/css/mezzanine1.css
drum/links/static/img/drum-logo.png
drum/links/static/img/glyphicons-halflings-white.png
drum/links/static/img/glyphicons-halflings.png
drum/links/static/js/bootstrap2-extras.js
drum/links/static/js/bootstrap2.js
drum/links/static/js/drum.js
drum/links/static/js/jquery.pjax.js
drum/links/templates/base.html
drum/links/templates/accounts/account_profile.html
drum/links/templates/accounts/includes/user_panel_nav.html
drum/links/templates/admin/links/link/change_list.html
drum/links/templates/generic/threadedcomment_list.html
drum/links/templates/generic/includes/comment.html
drum/links/templates/generic/includes/rating.html
drum/links/templates/includes/editable_loader.html
drum/links/templates/includes/pagination.html
drum/links/templates/includes/search_form.html
drum/links/templates/links/link_detail.html
drum/links/templates/links/link_form.html
drum/links/templates/links/link_list.html
drum/links/templates/links/tag_list.html
drum/links/templatetags/__init__.py
drum/links/templatetags/drum_tags.py
drum/project_template/__init__.py
drum/project_template/manage.py
drum/project_template/project_name/__init__.py
drum/project_template/project_name/local_settings.py.template
drum/project_template/project_name/settings.py
drum/project_template/project_name/urls.py
Drum-0.4.0.dist-info/DESCRIPTION.rst
Drum-0.4.0.dist-info/METADATA
Drum-0.4.0.dist-info/metadata.json
Drum-0.4.0.dist-info/RECORD
Drum-0.4.0.dist-info/top_level.txt
Drum-0.4.0.dist-info/WHEEL
